qingcloud_cli-1.3.12-py2.7-nspkg.pth
qingcloud/cli/__init__.py
qingcloud/cli/__init__.pyc
qingcloud/cli/completer.py
qingcloud/cli/completer.pyc
qingcloud/cli/driver.py
qingcloud/cli/driver.pyc
qingcloud/cli/iaas_client/__init__.py
qingcloud/cli/iaas_client/__init__.pyc
qingcloud/cli/iaas_client/handler.py
qingcloud/cli/iaas_client/handler.pyc
qingcloud/cli/iaas_client/actions/__init__.py
qingcloud/cli/iaas_client/actions/__init__.pyc
qingcloud/cli/iaas_client/actions/base.py
qingcloud/cli/iaas_client/actions/base.pyc
qingcloud/cli/iaas_client/actions/alarm_policy/__init__.py
qingcloud/cli/iaas_client/actions/alarm_policy/__init__.pyc
qingcloud/cli/iaas_client/actions/alarm_policy/add_alarm_policy_actions.py
qingcloud/cli/iaas_client/actions/alarm_policy/add_alarm_policy_actions.pyc
qingcloud/cli/iaas_client/actions/alarm_policy/add_alarm_policy_rules.py
qingcloud/cli/iaas_client/actions/alarm_policy/add_alarm_policy_rules.pyc
qingcloud/cli/iaas_client/actions/alarm_policy/apply_alarm_policy.py
qingcloud/cli/iaas_client/actions/alarm_policy/apply_alarm_policy.pyc
qingcloud/cli/iaas_client/actions/alarm_policy/associate_alarm_policy.py
qingcloud/cli/iaas_client/actions/alarm_policy/associate_alarm_policy.pyc
qingcloud/cli/iaas_client/actions/alarm_policy/create_alarm_policy.py
qingcloud/cli/iaas_client/actions/alarm_policy/create_alarm_policy.pyc
qingcloud/cli/iaas_client/actions/alarm_policy/delete_alarm_policies.py
qingcloud/cli/iaas_client/actions/alarm_policy/delete_alarm_policies.pyc
qingcloud/cli/iaas_client/actions/alarm_policy/delete_alarm_policy_actions.py
qingcloud/cli/iaas_client/actions/alarm_policy/delete_alarm_policy_actions.pyc
qingcloud/cli/iaas_client/actions/alarm_policy/delete_alarm_policy_rules.py
qingcloud/cli/iaas_client/actions/alarm_policy/delete_alarm_policy_rules.pyc
qingcloud/cli/iaas_client/actions/alarm_policy/describe_alarm_history.py
qingcloud/cli/iaas_client/actions/alarm_policy/describe_alarm_history.pyc
qingcloud_cli-1.3.12.dist-info/LICENSE
qingcloud_cli-1.3.12.dist-info/METADATA
qingcloud_cli-1.3.12.dist-info/NOTICE
qingcloud_cli-1.3.12.dist-info/WHEEL
qingcloud_cli-1.3.12.dist-info/namespace_packages.txt
qingcloud_cli-1.3.12.dist-info/top_level.txt
qingcloud_cli-1.3.12.dist-info/RECORD
