Metadata-Version: 2.1
Name: qingcloud-cli
Version: 1.3.12
Summary: Command Line Interface for QingCloud.
Home-page: https://docs.qingcloud.com
Author: Yunify Team
Author-email: simon@yunify.com
License: UNKNOWN
Keywords: qingcloud iaas qingstor cli
Platform: UNKNOWN
Requires-Dist: argparse (>=1.1)
Requires-Dist: PyYAML (>=3.1)
Requires-Dist: qingcloud-sdk (>=1.2.12)
